nseta/__init__.py
nseta/analytics/__init__.py
nseta/analytics/candle_rankings.py
nseta/analytics/model.py
nseta/archives/__init__.py
nseta/archives/archiver.py
nseta/cli/__init__.py
nseta/cli/historycli.py
nseta/cli/inputs.py
nseta/cli/livecli.py
nseta/cli/modelcli.py
nseta/cli/nsetacli.py
nseta/cli/plotscli.py
nseta/cli/strategycli.py
nseta/common/__init__.py
nseta/common/commons.py
nseta/common/constants.py
nseta/common/history.py
nseta/common/log.py
nseta/common/multithreadedScanner.py
nseta/common/symbols.py
nseta/common/ti.py
nseta/common/tradingtime.py
nseta/common/urls.py
nseta/live/__init__.py
nseta/live/live.py
nseta/live/liveurls.py
nseta/plots/__init__.py
nseta/plots/plots.py
nseta/resources/__init__.py
nseta/resources/config.txt
nseta/resources/resources.py
nseta/resources/stocks.txt
nseta/resources/userstocks.txt
nseta/scanner/__init__.py
nseta/scanner/baseScanner.py
nseta/scanner/baseStockScanner.py
nseta/scanner/intradayScanner.py
nseta/scanner/intradayStockScanner.py
nseta/scanner/liveScanner.py
nseta/scanner/liveStockScanner.py
nseta/scanner/newsScanner.py
nseta/scanner/quoteScanner.py
nseta/scanner/scannerFactory.py
nseta/scanner/stockNewsScanner.py
nseta/scanner/stockscanner.py
nseta/scanner/swingScanner.py
nseta/scanner/swingStockScanner.py
nseta/scanner/topPickScanner.py
nseta/scanner/topPickStockScanner.py
nseta/scanner/volumeScanner.py
nseta/scanner/volumeStockScanner.py
nseta/strategy/__init__.py
nseta/strategy/basesignalstrategy.py
nseta/strategy/bbandsSignalStrategy.py
nseta/strategy/macdSignalStrategy.py
nseta/strategy/rsiSignalStrategy.py
nseta/strategy/simulatedorder.py
nseta/strategy/strategy.py
nseta/strategy/strategyManager.py
tests/htmls/__init__.py
nseta-0.7.386.dist-info/LICENSE
nseta-0.7.386.dist-info/METADATA
nseta-0.7.386.dist-info/WHEEL
nseta-0.7.386.dist-info/entry_points.txt
nseta-0.7.386.dist-info/top_level.txt
nseta-0.7.386.dist-info/RECORD
