Metadata-Version: 2.1
Name: nseta
Version: 0.7.386
Summary: Library to scan, analyse and predict financial data from National Stock Exchange (NSE - India) in pandas dataframe 
Home-page: https://github.com/pkjmesra/nseta
Download-URL: https://github.com/pkjmesra/nseta/archive/v0.7.386.zip
Author: Praveen K Jha
Author-email: pkjmesra@gmail.com
License: OSI Approved (MIT)
Keywords: NSE,Technical Indicators,Backtesting,Forecasting
Platform: UNKNOWN
Classifier: License :: OSI Approved :: MIT License
Classifier: Operating System :: OS Independent
Classifier: Programming Language :: Python
Classifier: Programming Language :: Python :: 3
Classifier: Programming Language :: Python :: 3.7
Classifier: Programming Language :: Python :: 3.8
License-File: LICENSE
Requires-Dist: backtrader (>=1.9.75.123)
Requires-Dist: beautifulsoup4 (>=4.8.2)
Requires-Dist: black (>=19.10b0)
Requires-Dist: bs4 (>=0.0.1)
Requires-Dist: cachecontrol (>=0.12.6)
Requires-Dist: ccxt (>=1.51.84)
Requires-Dist: certifi (>=2019.11.28)
Requires-Dist: chardet (>=3.0.4)
Requires-Dist: Click (>=7.0)
Requires-Dist: cmdstanpy (>=0.9.5)
Requires-Dist: convertdate (>=2.3.0)
Requires-Dist: croniter (>=0.3.35)
Requires-Dist: Cython (>=0.22)
Requires-Dist: idna (>=2.8)
Requires-Dist: LunarCalendar (>=0.0.9)
Requires-Dist: lxml (>=4.6.2)
Requires-Dist: matplotlib (>=3.2.2)
Requires-Dist: networkx (>=2.4)
Requires-Dist: numpy (>=1.18.0)
Requires-Dist: oauthlib (>=3.1.0)
Requires-Dist: pandas (>=1.1.2)
Requires-Dist: plotly (>=4.14.3)
Requires-Dist: pybind11 (>=2.6.2)
Requires-Dist: PySocks (>=1.7.1)
Requires-Dist: pystan (==2.19.1.1)
Requires-Dist: python-dateutil (>=2.8.0)
Requires-Dist: pytz (>=2019.3)
Requires-Dist: requests (>=2.22.0)
Requires-Dist: requests-oauthlib (>=1.3.0)
Requires-Dist: setuptools (>=50.3.0)
Requires-Dist: setuptools-git (>=1.2)
Requires-Dist: six (>=1.13.0)
Requires-Dist: soupsieve (>=1.9.5)
Requires-Dist: tqdm (>=4.36.1)
Requires-Dist: tweepy (>=3.8.0)
Requires-Dist: urllib3 (>=1.25.7)
Requires-Dist: yfinance (>=0.1.54)
Requires-Dist: nltk (>=3.5)
Requires-Dist: pre-commit
Requires-Dist: scipy (>=1.5.2)
Requires-Dist: wheel (>=0.35.1)
